{
   "product":[
      {
         "image":"https://global-uploads.webflow.com/5d556af3fe21d65f602dca94/5ef0a2ef51ef17a783edf2d6_Order%20%23538882%20%7C%20jamie%40somethingnavy.com%202.jpg",
         "productName":"Nude color sweater",
         "category":[
            "female",
            "sweater"
         ],
         "price":"400",
         "size":"L",
         "description":"Nude color sweater",
         "email":"aaa@gmail.com",
         "code":"1865321",
         "date":"12565654121"
      },
      {
         "image":"https://global-uploads.webflow.com/5d552994548be47b97db38c2/5deab13bf88fbc95f8271e6e_11-2.jpg",
         "productName":"Grey sweater",
         "category":[
            "male",
            "sweater"
         ],
         "price":"450",
         "size":"M",
         "description":"Grey basic sweater for men",
         "email":"bbba@gmail.com",
         "code":"1456821",
         "date":"13655654121"
      },
      {
         "image":"https://ae01.alicdn.com/kf/H477def96a0f14b8b954a30528d137c70W.jpg",
         "productName":"Pink sweatshirt",
         "category":[
            "female",
            "sweater"
         ],
         "price":"500",
         "size":"S",
         "description":"Short-waist pink sweatshirt",
         "email":"jk@yahoo.com",
         "code":"4789521",
         "date":"15796444121"
      },
      {
         "image":"https://www.berluti.com/on/demandware.static/-/Sites-masterCatalog_Berluti/default/dw5b7aa9db/images/R16TCU57-002_slim-fit-cotton-chino-pants_pleiades_berluti_01.jpg",
         "productName":"Male blue pants",
         "category":[
            "male",
            "pants"
         ],
         "price":"650",
         "size":"M",
         "description":"Blue elegant pants",
         "email":"pantsSeller@gmail.com",
         "code":"8767641",
         "date":"12563635621"
      },
      {
         "image":"https://www.xtremeinn.com/f/13816/138164466/dickies-comba-elasticated-cargo-pants.jpg",
         "productName":"Cargo Pants",
         "category":[
            "male",
            "pants"
         ],
         "price":"650",
         "size":"S",
         "description":"Nude color cargo pants for men. In an excellent condition.",
         "email":"cargo@gmail.com",
         "code":"1855321",
         "date":"1256555521"
      },
      {
         "image":"https://img.joomcdn.net/01ea0ff1abd878fe3bf75bd0338eea3423306bf5_original.jpeg",
         "productName":"Pink loose skirt",
         "category":[
            "female",
            "skirts"
         ],
         "price":"400",
         "size":"S",
         "description":"A loose and long pink skirt, with a bow on the left side. Elegant for ceremonies and festive events.",
         "email":"bow@gmail.com",
         "code":"6845561",
         "date":"12565654121"
      },
      {
         "image":"https://assets.vogue.com/photos/5f5bd7c5c287ced7cb397c01/master",
         "productName":"White elegant pents",
         "category":[
            "female",
            "pants"
         ],
         "price":"400",
         "size":"S",
         "description":"Loose beige-color elegant pants",
         "email":"newP@gmail.com",
         "code":"7852821",
         "date":"1259764121"
      },
      {
         "image":"https://images-eu.ssl-images-amazon.com/images/I/71ejwh9ZVYL.jpg",
         "productName":"Leather blue backpack",
         "category":[
            "female",
            "bags"
         ],
         "price":"600",
         "size":"One Size",
         "description":"Leather backpack(Bluesky color). ",
         "email":"aaa@gmail.com",
         "code":"7123551",
         "date":"125656845121"
      },
      {
         "image":"https://st.mngbcn.com/rcs/pics/static/T8/fotos/S20/87045646_CU_B.jpg?ts=1612425525050&imwidth=388&imdensity=2",
         "productName":"Brown bag",
         "category":[
            "female",
            "bags"
         ],
         "price":"350",
         "size":"One Size",
         "description":"Brown leather bag. Barely used, in a great condition.",
         "email":"aaa@gmail.com",
         "code":"7895321",
         "date":"12565654121"
      },
      {
         "image":"https://images.squarespace-cdn.com/content/v1/548ec3bee4b068057bfb6db7/1555524366324-VWFSC5FC2C2D9IP7XCP7/image-asset.jpeg?format=1500w",
         "productName":"Summer print backpack",
         "category":[
            "female",
            "bags"
         ],
         "price":"250",
         "size":"One Size",
         "description":"Backpack with sunset on the beach print. Beautiful for everyday activities",
         "email":"gm@gmail.com",
         "code":"7367541",
         "date":"12565654121"
      },
      {
         "image":"https://i.pinimg.com/originals/e8/85/15/e88515b6eef134073bdc97a7645bf360.jpg",
         "productName":"Beige color pouch",
         "category":[
            "female",
            "bags"
         ],
         "price":"400",
         "size":"One Size",
         "description":"Beige color bag. In a perfect condition",
         "email":"kkk@gmail.com",
         "code":"2135136",
         "date":"1256684521"
      },
      {
         "image":"https://www.fjallraven.com/4921cb/globalassets/catalogs/fjallraven/f7/f780/f78011/f662/7323450521226_fw19_a_solid_rewool_scarf_fjaellraeven_21.jpg?width=2000&height=2000&mode=BoxPad&bgcolor=fff&quality=80",
         "productName":"Dark green scarf",
         "category":[
            "female",
            "accessories"
         ],
         "price":"300",
         "size":"One Size",
         "description":"Dark green olive-color scarf.",
         "email":"bba@gmail.com",
         "code":"8555321",
         "date":"12565654121"
      },
      {
         "image":"https://www.bodenimages.com/productimages/zoom/20wwin_a0807_nav.jpg",
         "productName":"Winter scarf",
         "category":[
            "female",
            "accessories"
         ],
         "price":"250",
         "size":"One Size",
         "description":"A perfect warm scarf for the winter.",
         "email":"a@gmail.com",
         "code":"1566721",
         "date":"12565654121"
      },
      {
         "image":"https://staticimg.titan.co.in/Tanishq/Catalog/502997SQOABA02_1.jpg?impolicy=pqmed&imwidth=640",
         "productName":"Little stars earrings",
         "category":[
            "female",
            "accessories"
         ],
         "price":"100",
         "size":"One Size",
         "description":"Static short earrings, beautiful for every type of event.",
         "email":"gm@gmail.com",
         "code":"7777321",
         "date":"12565654121"
      },
      {
         "image":"https://media.sezane.com/image/upload/c_fill,d_placeholder_dark.png,fl_progressive:semi,h_816,q_auto:best,w_582/hjrhlo8gvqlthnuwvzkn.jpg",
         "productName":"Hoop earrings",
         "category":[
            "female",
            "accessories"
         ],
         "price":"300",
         "size":"One Size",
         "description":"Ring earrings with many pearls nice for elegant events. In a perfect condition.",
         "email":"gm@gmail.com",
         "code":"1865321",
         "date":"12565654121"
      },
      {
         "image":"https://www.allthefallingstars.com/wp-content/uploads/2020/05/P7250506.jpg",
         "productName":"Ring earings",
         "category":[
            "female",
            "accessories"
         ],
         "price":"400",
         "size":"One Size",
         "description":"",
         "email":"gm@gmail.com",
         "code":"1865321",
         "date":"12565654121"
      },
      {
         "image":"https://static.cilory.com/273124-thickbox_default/nologo-navy-casual-shirt.jpg",
         "productName":"Shirt",
         "category":[
            "male",
            "shirts"
         ],
         "price":"400",
         "size":"L",
         "description":"Checked shirt with long sleeves, good quality, not very used",
         "email":"aaa@gmail.com",
         "code":"1111111",
         "date":"12565654121"
      },
      {
         "image":"https://image.uniqlo.com/UQ/ST3/AsianCommon/imagesgoods/437243/item/goods_18_437243.jpg?width=1600&impolicy=quality_75",
         "productName":"Pink tshirt",
         "category":[
            "male",
            "tshirts"
         ],
         "price":"250",
         "size":"M",
         "description":"Pink cotton tshirt, short sleeves and pocket",
         "email":"bbb@gmail.com",
         "code":"1111111",
         "date":"12565654121"
      },
      {
         "image":"https://imgs.michaels.com/MAM/assets/1/726D45CA1C364650A39CD1B336F03305/img/893E44B4248847338CD88E85BD79D361/10186027_r.jpg?fit=inside|140:140,https://imgs.michaels.com/MAM/assets/1/726D45CA1C364650A39CD1B336F03305/img/893E44B4248847338CD88E85BD79D361/10186027_r.jpg?fit=inside|220:220,https://imgs.michaels.com/MAM/assets/1/726D45CA1C364650A39CD1B336F03305/img/893E44B4248847338CD88E85BD79D361/10186027_r.jpg?fit=inside|540:540",
         "productName":"tshirt",
         "category":[
            "male",
            "tshirts"
         ],
         "price":"200",
         "size":"M",
         "description":"Blue tshirt with short sleeves, medium quality, cotton and polyester",
         "email":"ccc@gmail.com",
         "code":"1111111",
         "date":"12565654121"
      },
      {
         "image":"https://www.brother2brother.co.uk/images/black-white-embroidered-swallow-t-shirt-p19088-49633_zoom.jpg",
         "productName":"Black tshirt with print",
         "category":[
            "male",
            "tshirts"
         ],
         "price":"350",
         "size":"L",
         "description":"Blue tshirt with short sleeves and bird print, high quality",
         "email":"ddd@gmail.com",
         "code":"1111111",
         "date":"12565654121"
      },
      {
         "image":"https://images.sportsdirect.com/images/products/44488169_l.jpg",
         "productName":"Purple tshirt with illustration",
         "category":[
            "female",
            "tshirts"
         ],
         "price":"300",
         "size":"S",
         "description":"Purple tshirt with tree illustration, short sleeves, cotton, medium quality",
         "email":"ggg@gmail.com",
         "code":"1111111",
         "date":"12565654121"
      },
      {
         "image":"https://m.media-amazon.com/images/I/71V1X38KiiL._UX569_.jpg",
         "productName":"Summer dress with sunflower print",
         "category":[
            "female",
            "dresses"
         ],
         "price":"400",
         "size":"XS",
         "description":"Sunflower print dress, not very used",
         "email":"eee@gmail.com",
         "code":"1111111",
         "date":"12565654121"
      },
      {
         "image":"https://cdn.shopify.com/s/files/1/0663/7293/products/product-image-915454867.jpg?v=1591006732",
         "productName":"Dark blue girl dress",
         "category":[
            "female",
            "dresses"
         ],
         "price":"450",
         "size":"M",
         "description":"Female dress, dark blue, used once",
         "email":"fff@gmail.com",
         "code":"1111111",
         "date":"12565654121"
      },
      {
         "image":"https://static.cilory.com/273124-thickbox_default/nologo-navy-casual-shirt.jpg",
         "productName":"Shirt",
         "category":[
            "female",
            "sweaters"
         ],
         "price":"400",
         "size":"L",
         "description":"Checked shirt with long sleeves, good quality, not very used",
         "email":"aaa@gmail.com",
         "code":"1111111",
         "date":"12565654121"
      },
      {
         "image":"https://i.pinimg.com/564x/fb/3f/57/fb3f57ca63bbc31979bb5a2d6f49a77b.jpg",
         "productName":"Smiley black sweater",
         "category":[
            "female",
            "dresses"
         ],
         "price":"300",
         "size":"L",
         "description":"High quality black girl sweater, smiley print",
         "email":"hhh@gmail.com",
         "code":"1111111",
         "date":"12565654121"
      },
      {
         "image":"https://i.pinimg.com/564x/fb/3f/57/fb3f57ca63bbc31979bb5a2d6f49a77b.jpg",
         "productName":"Black sunglasses",
         "category":[
            "female",
            "accessories"
         ],
         "price":"300",
         "size":"OneSize",
         "description":"Black sunglasses girls accessories",
         "email":"jjj@gmail.com",
         "code":"1111111",
         "date":"12565654121"
      },
      {
         "image":"https://i.pinimg.com/564x/fe/8d/a9/fe8da925b47b6a2274f6026cec4517ba.jpg",
         "productName":"Black bag",
         "category":[
            "female",
            "bags"
         ],
         "price":"200",
         "size":"OneSize",
         "description":"Black girl bag, the zipper does not work",
         "email":"nnn@gmail.com",
         "code":"1111111",
         "date":"12565654121"
      },
      {
         "image":"https://i.pinimg.com/564x/9b/99/ef/9b99efa982a9f3fd22773a5608eebb99.jpg",
         "productName":"Zebra bag",
         "category":[
            "female",
            "bags"
         ],
         "price":"350",
         "size":"OneSize",
         "description":"Small bag with zebra print, medium quality",
         "email":"mmm@gmail.com",
         "code":"1111111",
         "date":"12565654121"
      },
      {
         "image":"https://i.pinimg.com/564x/c6/00/6d/c6006de273b34f146e21c353eef9ad71.jpg",
         "productName":"Girl shorts",
         "category":[
            "female",
            "pants"
         ],
         "price":"400",
         "size":"L",
         "description":"High waist shorts, medium quality",
         "email":"yyy@gmail.com",
         "code":"1111111",
         "date":"12565654121"
      },
      {
         "image":"https://i.pinimg.com/564x/39/5e/66/395e668c0c1607c53076a5bd5dc9a3aa.jpg",
         "productName":"Black jeans",
         "category":[
            "female",
            "pants"
         ],
         "price":"300",
         "size":"M",
         "description":"High waist straight leg black girls jeans with build in belt",
         "email":"uuu@gmail.com",
         "code":"1111111",
         "date":"12565654121"
      },
      {
         "image":"https://i.pinimg.com/564x/05/aa/2f/05aa2fb03c53f8362cab439c29cea619.jpg",
         "productName":"Black wool sweater",
         "category":[
            "female",
            "sweaters"
         ],
         "price":"400",
         "size":"L",
         "description":"High quality black sweater, cotton and wool",
         "email":"eee@gmail.com",
         "code":"1111111",
         "date":"12565654121"
      },
      {
         "image":"https://i.pinimg.com/564x/7f/5a/e1/7f5ae1c6682e7d8198d2b5c2b7f8f0b0.jpg",
         "productName":"Checked pants",
         "category":[
            "female",
            "pants"
         ],
         "price":"400",
         "size":"M",
         "description":"Checked cotton woman pants, medium quality",
         "email":"iii@gmail.com",
         "code":"1111111",
         "date":"12565654121"
      }
   ]
}